recordlinkage/__init__.py
recordlinkage/_version.py
recordlinkage/adapters.py
recordlinkage/annotation.py
recordlinkage/api.py
recordlinkage/base.py
recordlinkage/classifiers.py
recordlinkage/compare.py
recordlinkage/config.py
recordlinkage/config_init.py
recordlinkage/deprecated.py
recordlinkage/index.py
recordlinkage/measures.py
recordlinkage/network.py
recordlinkage/rl_logging.py
recordlinkage/types.py
recordlinkage/utils.py
recordlinkage/_lib/numeric.c
recordlinkage/_lib/numeric.h
recordlinkage/algorithms/__init__.py
recordlinkage/algorithms/c_numeric.pyx
recordlinkage/algorithms/compare.py
recordlinkage/algorithms/distance.py
recordlinkage/algorithms/indexing.py
recordlinkage/algorithms/nb_sklearn.py
recordlinkage/algorithms/numeric.py
recordlinkage/algorithms/string.py
recordlinkage/contrib/README.rst
recordlinkage/contrib/__init__.py
recordlinkage/contrib/compare/__init__.py
recordlinkage/contrib/compare/random/README.rst
recordlinkage/contrib/compare/random/__init__.py
recordlinkage/contrib/compare/random/random.py
recordlinkage/contrib/index/__init__.py
recordlinkage/contrib/index/neighbourhoodblock/README.rst
recordlinkage/contrib/index/neighbourhoodblock/__init__.py
recordlinkage/contrib/index/neighbourhoodblock/neighbourhoodblock.py
recordlinkage/datasets/__init__.py
recordlinkage/datasets/external.py
recordlinkage/datasets/febrl.py
recordlinkage/datasets/generate.py
recordlinkage/datasets/febrl/dataset1.csv
recordlinkage/datasets/febrl/dataset2.csv
recordlinkage/datasets/febrl/dataset3.csv
recordlinkage/datasets/febrl/dataset4a.csv
recordlinkage/datasets/febrl/dataset4b.csv
recordlinkage/preprocessing/__init__.py
recordlinkage/preprocessing/cleaning.py
recordlinkage/preprocessing/encoding.py
recordlinkage/standardise/__init__.py
recordlinkage-0.16.dist-info/LICENSE
recordlinkage-0.16.dist-info/METADATA
recordlinkage-0.16.dist-info/WHEEL
recordlinkage-0.16.dist-info/top_level.txt
recordlinkage-0.16.dist-info/RECORD
