Metadata-Version: 2.1
Name: recordlinkage
Version: 0.16
Summary: A record linkage toolkit for linking and deduplication
Author-email: Jonathan de Bruin <jonathandebruinos@gmail.com>
License: BSD-3-Clause
Project-URL: homepage, https://recordlinkage.readthedocs.io/
Project-URL: repository, https://github.com/J535D165/recordlinkage
Classifier: Development Status :: 4 - Beta
Classifier: License :: OSI Approved :: BSD License
Classifier: Programming Language :: Python :: 3.8
Classifier: Programming Language :: Python :: 3.9
Classifier: Programming Language :: Python :: 3.10
Classifier: Programming Language :: Python :: 3.11
Requires-Python: >=3.8
Provides-Extra: all
Provides-Extra: lint
Provides-Extra: docs
Provides-Extra: test
License-File: LICENSE
